betterterminalcli/__init__.py
betterterminalcli/core/__init__.py
betterterminalcli/core/screen_buffer.py
betterterminalcli/core/terminal_app.py
betterterminalcli/widgets/__init__.py
betterterminalcli/widgets/base_widget.py
betterterminalcli/widgets/text_widget.py
betterterminalcli-0.1.1.dist-info/licenses/LICENSE
betterterminalcli-0.1.1.dist-info/METADATA
betterterminalcli-0.1.1.dist-info/WHEEL
betterterminalcli-0.1.1.dist-info/top_level.txt
betterterminalcli-0.1.1.dist-info/RECORD
