Metadata-Version: 2.4
Name: betterterminalcli
Version: 0.1.1
Summary: Uma biblioteca para facilitar interfaces no terminal com menus, formulários, tabelas, logs coloridos e mais.
Home-page: https://github.com/MauricioReisdoefer/better-terminal-cli
Author: Maurício Reisdoefer Pereira
Author-email: mauricio.reisdoefer2009@gmail.com
Classifier: Programming Language :: Python :: 3
Classifier: Operating System :: OS Independent
Classifier: Topic :: Software Development :: Libraries
Classifier: Topic :: Utilities
Classifier: License :: OSI Approved :: MIT License
Requires-Python: >=3.8
License-File: LICENSE
Requires-Dist: readchar>=3.0.0
Dynamic: author
Dynamic: author-email
Dynamic: classifier
Dynamic: description
Dynamic: description-content-type
Dynamic: home-page
Dynamic: license-file
Dynamic: requires-dist
Dynamic: requires-python
Dynamic: summary
